{
    "contacts": [
       {
            "contact": 0,
            "source": 1,
            "dest": 10,
            "finalDestination": 2,
            "startTime": 0,
            "endTime": 2000,
            "rateBitsPerSec": 0,
            "owlt":  1
        },
        {
            "contact": 3,
            "source": 10,
            "dest": 1,
            "finalDestination": 1,
            "startTime": 0,
            "endTime": 2000,
            "rateBitsPerSec": 0,
            "owlt": 1
        },
        {
            "contact": 4,
            "source": 10,
            "dest": 102,
            "finalDestination": 102,
            "startTime": 0,
            "endTime": 2000,
            "rateBitsPerSec": 0,
            "owlt": 1
        }
    ]
}
